ovos_skill_naptime/LICENSE
ovos_skill_naptime/MANIFEST.in
ovos_skill_naptime/README.md
ovos_skill_naptime/__init__.py
ovos_skill_naptime/requirements.txt
ovos_skill_naptime/version.py
ovos_skill_naptime/locale/ca-es/SleepCommand.voc
ovos_skill_naptime/locale/ca-es/going.to.sleep.dialog
ovos_skill_naptime/locale/ca-es/going.to.sleep.short.dialog
ovos_skill_naptime/locale/ca-es/i.am.awake.dialog
ovos_skill_naptime/locale/ca-es/naptime.intent
ovos_skill_naptime/locale/ca-es/skill.json
ovos_skill_naptime/locale/ca-es/wakeup.voc
ovos_skill_naptime/locale/cs-cz/SleepCommand.voc
ovos_skill_naptime/locale/cs-cz/going.to.sleep.dialog
ovos_skill_naptime/locale/cs-cz/going.to.sleep.short.dialog
ovos_skill_naptime/locale/cs-cz/i.am.awake.dialog
ovos_skill_naptime/locale/da-dk/going.to.sleep.dialog
ovos_skill_naptime/locale/da-dk/going.to.sleep.short.dialog
ovos_skill_naptime/locale/da-dk/i.am.awake.dialog
ovos_skill_naptime/locale/da-dk/naptime.intent
ovos_skill_naptime/locale/da-dk/skill.json
ovos_skill_naptime/locale/da-dk/wakeup.voc
ovos_skill_naptime/locale/de-de/SleepCommand.voc
ovos_skill_naptime/locale/de-de/going.to.sleep.dialog
ovos_skill_naptime/locale/de-de/going.to.sleep.short.dialog
ovos_skill_naptime/locale/de-de/i.am.awake.dialog
ovos_skill_naptime/locale/de-de/naptime.intent
ovos_skill_naptime/locale/de-de/skill.json
ovos_skill_naptime/locale/de-de/wakeup.voc
ovos_skill_naptime/locale/el-gr/going.to.sleep.dialog
ovos_skill_naptime/locale/el-gr/going.to.sleep.short.dialog
ovos_skill_naptime/locale/el-gr/i.am.awake.dialog
ovos_skill_naptime/locale/en-us/going.to.sleep.dialog
ovos_skill_naptime/locale/en-us/going.to.sleep.short.dialog
ovos_skill_naptime/locale/en-us/i.am.awake.dialog
ovos_skill_naptime/locale/en-us/naptime.intent
ovos_skill_naptime/locale/en-us/skill.json
ovos_skill_naptime/locale/en-us/wakeup.voc
ovos_skill_naptime/locale/es-es/SleepCommand.voc
ovos_skill_naptime/locale/es-es/going.to.sleep.dialog
ovos_skill_naptime/ovos_skill_naptime.egg-info/PKG-INFO
ovos_skill_naptime/ovos_skill_naptime.egg-info/SOURCES.txt
ovos_skill_naptime/ovos_skill_naptime.egg-info/dependency_links.txt
ovos_skill_naptime/ovos_skill_naptime.egg-info/entry_points.txt
ovos_skill_naptime/ovos_skill_naptime.egg-info/requires.txt
ovos_skill_naptime/ovos_skill_naptime.egg-info/top_level.txt
ovos_skill_naptime-0.3.15.dist-info/LICENSE
ovos_skill_naptime-0.3.15.dist-info/METADATA
ovos_skill_naptime-0.3.15.dist-info/WHEEL
ovos_skill_naptime-0.3.15.dist-info/entry_points.txt
ovos_skill_naptime-0.3.15.dist-info/top_level.txt
ovos_skill_naptime-0.3.15.dist-info/RECORD
