Metadata-Version: 2.1
Name: ovos-skill-naptime
Version: 0.3.15
Summary: ovos skill plugin
Home-page: https://github.com/OpenVoiceOS/ovos-skill-naptime
Author: JarbasAi
Author-email: jarbasai@mailfence.com
License: Apache-2.0
Keywords: ovos skill plugin
License-File: LICENSE
Requires-Dist: ovos-utils>=0.0.38
Requires-Dist: ovos-workshop<8.0.0,>=0.0.15
Requires-Dist: ovos-bus-client<2.0.0,>=1.2.0
